py_monnify/__init__.py
py_monnify/module.py
py_monnify-0.0.6.dist-info/METADATA
py_monnify-0.0.6.dist-info/WHEEL
py_monnify-0.0.6.dist-info/top_level.txt
py_monnify-0.0.6.dist-info/RECORD
