Metadata-Version: 2.1
Name: py-monnify
Version: 0.0.6
Summary: Monnify payment module for python developer
Home-page: https://github.com/samwhitedove/python_for_monnify
Download-URL: https://github.com/samwhitedove/python_for_monnify
Author: Smarttek
Author-email: <samwhitedove@gmail.com>
Maintainer: smarttek
Maintainer-email: samwhitedove@gmail.com
License: OSI Approved :: MIT License
Keywords: python,payment,gateway,monnify,payment gateway
Classifier: Development Status :: 1 - Planning
Classifier: Intended Audience :: Developers
Classifier: License :: OSI Approved :: MIT License
Classifier: Programming Language :: Python :: 3
Classifier: Operating System :: Unix
Classifier: Operating System :: MacOS :: MacOS X
Classifier: Operating System :: Microsoft :: Windows
Requires-Dist: requests
